{
    "entityName": "Company",
    "label": {
        "de": "Lorem Ipsum - de",
        "en": "Lorem Ipsum - en"
    },
    "alternativeLabel": {
        "de": "alt Lorem Ipsum",
        "en": null
    },
    "description": {
        "de": "dummy - de",
        "en": "dummy - en"
    },
    "fields": [
        {
            "name": "avgDebtTotalInterest",
            "value": "core"
        },
        {
            "name": "avgFixedInterestPeriod",
            "value": "not"
        },
        {
            "name": "avgFxForwardTotalTerm"
        }
    ],
    "subEntities": [
        {
            "entityName": "PartnerLink",
            "label": {
                "de": "Lorem Ipsum - de",
                "en": "Lorem Ipsum - en"
            },
            "alternativeLabel": {
                "de": "alt Lorem Ipsum",
                "en": null
            },
            "description": {
                "de": "dummy - de",
                "en": "dummy - en"
            },
            "fields": [],
            "subEntities": []
        }
    ]
}